{
	"albany": {
		"canonicalName": "Albany",
		"state": "ny"
	},
	"albuquerque": {
		"canonicalName": "Albuquerque",
		"state": "nm"
	},
	"atlanta": {
		"canonicalName": "Atlanta",
		"state": "ga"
	},
	"austin": {
		"canonicalName": "Austin",
		"state": "tx"
	},
	"bangalore": {
		"canonicalName": "Bangalore",
		"state": "karnataka"
	},
	"bengaluru": {
		"canonicalName": "Bangalore",
		"state": "karnataka"
	},
	"bellevue": {
		"canonicalName": "Bellevue",
		"state": "wa"
	},
	"bentonville": {
		"canonicalName": "Bentonville",
		"state": "ak"
	},
	"boston": {
		"canonicalName": "Boston",
		"state": "ma"
	},
	"boulder": {
		"canonicalName": "Boulder",
		"state": "co"
	},
	"calgary": {
		"canonicalName": "Calgary",
		"state": "alberta"
	},
	"cary": {
		"canonicalName": "Cary",
		"state": "nc"
	},
	"charleston": {
		"canonicalName": "Charleston",
		"state": "sc"
	},
	"charlotte": {
		"canonicalName": "Charlotte",
		"state": "nc"
	},
	"chicago": {
		"canonicalName": "Chicago",
		"state": "il"
	},
	"cleveland": {
		"canonicalName": "Cleveland",
		"state": "oh"
	},
	"columbus": {
		"canonicalName": "Columbus",
		"state": "oh"
	},
	"dallas": {
		"canonicalName": "Dallas",
		"state": "tx"
	},
	"denver": {
		"canonicalName": "Denver",
		"state": "co"
	},
	"fort-myers": {
		"canonicalName": "Fort Myers",
		"state": "fl"
	},
	"fort-worth": {
		"canonicalName": "Fort Worth",
		"state": "tx"
	},
	"ft-worth": {
		"canonicalName": "Fort Worth",
		"state": "tx"
	},
	"fremont": {
		"canonicalName": "Fremont",
		"state": "wa"
	},
	"houston": {
		"canonicalName": "Houston",
		"state": "tx"
	},
	"irvine": {
		"canonicalName": "Irvine",
		"state": "ca"
	},
	"kirkland": {
		"canonicalName": "Kirkland",
		"state": "wa"
	},
	"liberty-lake": {
		"canonicalName": "Liberty Lake",
		"state": "wa"
	},
	"london": {
		"canonicalName": "London",
		"state": "england"
	},
	"los-angeles": {
		"canonicalName": "Los Angeles",
		"state": "ca"
	},
	"la": {
		"canonicalName": "Los Angeles",
		"state": "ca"
	},
	"manhattan-beach": {
		"canonicalName": "Manhattan Beach",
		"state": "ca"
	},
	"mcallen": {
		"canonicalName": "McAllen",
		"state": "tx"
	},
	"melbourne": {
		"canonicalName": "Melbourne",
		"state": "victoria"
	},
	"miami": {
		"canonicalName": "Miami",
		"state": "fl"
	},
	"minneapolis": {
		"canonicalName": "Minneapolis",
		"state": "mn"
	},
	"montreal": {
		"canonicalName": "Montreal",
		"state": "qc"
	},
	"morrisville": {
		"canonicalName": "Morrisville",
		"state": "nc"
	},
	"mountain-view": {
		"canonicalName": "Mountain View",
		"state": "ca"
	},
	"munich": {
		"canonicalName": "Munich",
		"state": "bavaria"
	},
	"new-york": {
		"canonicalName": "New York",
		"state": "ny"
	},
	"new-york-city": {
		"canonicalName": "New York",
		"state": "ny"
	},
	"ny": {
		"canonicalName": "New York",
		"state": "ny"
	},
	"nyc": {
		"canonicalName": "New York",
		"state": "ny"
	},
	"norfolk": {
		"canonicalName": "Norfolk",
		"state": "va"
	},
	"palo-alto": {
		"canonicalName": "Palo Alto",
		"state": "ca"
	},
	"phoenix": {
		"canonicalName": "Pheonix",
		"state": "az"
	},
	"philadelphia": {
		"canonicalName": "Philadelphia",
		"state": "pa"
	},
	"portland": {
		"canonicalName": "Portland",
		"state": "or"
	},
	"pdx": {
		"canonicalName": "Portland",
		"state": "or"
	},
	"providence": {
		"canonicalName": "Providence",
		"state": "ri"
	},
	"queen-anne": {
		"canonicalName": "Queen Anne",
		"state": "wa"
	},
	"raleigh": {
		"canonicalName": "Raleigh",
		"state": "nc"
	},
	"redmond": {
		"canonicalName": "Redmond",
		"state": "wa"
	},
	"redwood-city": {
		"canonicalName": "Redwood City",
		"state": "ca"
	},
	"richmond": {
		"canonicalName": "Richmond",
		"state": "va"
	},
	"riverside": {
		"canonicalName": "Riverside",
		"state": "ca"
	},
	"sacramento": {
		"canonicalName": "Sacramento",
		"state": "ca"
	},
	"san-antonio": {
		"canonicalName": "San Antonio",
		"state": "tx"
	},
	"san-diego": {
		"canonicalName": "San Diego",
		"state": "ca"
	},
	"san-francisco": {
		"canonicalName": "San Francisco",
		"state": "ca"
	},
	"san-jose": {
		"canonicalName": "San Jose",
		"state": "ca"
	},
	"bay-area": {
		"canonicalName": "San Francisco",
		"state": "ca"
	},
	"sf": {
		"canonicalName": "San Francisco",
		"state": "ca"
	},
	"sfo": {
		"canonicalName": "San Francisco",
		"state": "ca"
	},
	"san-mateo": {
		"canonicalName": "San Mateo",
		"state": "ca"
	},
	"seattle": {
		"canonicalName": "Seattle",
		"state": "wa"
	},
	"st-louis": {
		"canonicalName": "St. Louis",
		"state": "mo"
	},
	"stafford": {
		"canonicalName": "Stafford",
		"state": "va"
	},
	"sunnyvale": {
		"canonicalName": "Sunnyvale",
		"state": "ca"
	},
	"sydney": {
		"canonicalName": "Sydney",
		"state": "new-south-wales"
	},
	"tokyo": {
		"canonicalName": "Tokyo",
		"state": "tokyo"
	},
	"toronto": {
		"canonicalName": "Toronto",
		"state": "ontario"
	},
	"tucson": {
		"canonicalName": "Tucson",
		"state": "az"
	},
	"vancouver": {
		"canonicalName": "Vancouver",
		"state": "british-columbia"
	}
}
